MANIFEST.in
README.rst
setup.py
Core_Selenium.egg-info/PKG-INFO
Core_Selenium.egg-info/SOURCES.txt
Core_Selenium.egg-info/dependency_links.txt
Core_Selenium.egg-info/not-zip-safe
Core_Selenium.egg-info/top_level.txt
main/__init__.py
main/com_logigear/__init__.py
main/com_logigear/constant/__init__.py
main/com_logigear/constant/constants.py
main/com_logigear/driver/__init__.py
main/com_logigear/driver/driver.py
main/com_logigear/driver/driver_manager.py
main/com_logigear/driver/driver_properties.py
main/com_logigear/driver/browser/__init__.py
main/com_logigear/driver/browser/desktop_chrome_driver.py
main/com_logigear/driver/browser/desktop_firefox_driver.py
main/com_logigear/driver/browser/desktop_internet_explorer_driver.py
main/com_logigear/driver/browser/desktop_safari_driver.py
main/com_logigear/driver/cloud/__init__.py
main/com_logigear/driver/cloud/sauce_labs_driver.py
main/com_logigear/driver/mobile/__init__.py
main/com_logigear/driver/mobile/mobile_android_driver.py
main/com_logigear/driver/mobile/mobile_iosdriver.py
main/com_logigear/element/BaseElement.py
main/com_logigear/element/__init__.py
main/com_logigear/element/common/Button.py
main/com_logigear/element/common/Label.py
main/com_logigear/element/common/Textbox.py
main/com_logigear/element/common/__init__.py
resources/__init__.py