Metadata-Version: 1.0
Name: Core-Selenium
Version: 0.1.2
Summary: Selenium framework source code
Home-page: http://tfs.logigear.com/SD/SeleniumCore/_git/PythonSeleniumCore
Author: Khoi Ngo
Author-email: quainhan100@gmail.com
License: MIT
Keywords: selenium core ngo anh khoi
Platform: UNKNOWN
